pyhop/__init__.py
pyhop/main.py
pyhop-0.0.6.dist-info/METADATA
pyhop-0.0.6.dist-info/WHEEL
pyhop-0.0.6.dist-info/top_level.txt
pyhop-0.0.6.dist-info/RECORD
