Metadata-Version: 2.1
Name: pyhop
Version: 0.0.6
Summary: This project is a Python script that utilizes built-in trace tools like tracert for Windows and traceroute for Linux to perform a traceroute to a given hostname or IP address. It traces the path that packets take from your device to the destination host, providing ip addresses
Author: Sarthak
Author-email: <waliasarthak@gmail.com>
Keywords: python,traceroute,tracert,hops,ip address,server hops
Classifier: Development Status :: 1 - Planning
Classifier: Intended Audience :: Developers
Classifier: Programming Language :: Python :: 3
Classifier: Operating System :: Unix
Classifier: Operating System :: Microsoft :: Windows
